kitten_mcp_server/__init__.py
kitten_mcp_server/__main__.py
kitten_mcp_server/main.py
kitten_mcp_server-0.1.0.dist-info/licenses/LICENSE
kitten_mcp_server-0.1.0.dist-info/METADATA
kitten_mcp_server-0.1.0.dist-info/WHEEL
kitten_mcp_server-0.1.0.dist-info/entry_points.txt
kitten_mcp_server-0.1.0.dist-info/top_level.txt
kitten_mcp_server-0.1.0.dist-info/RECORD
