Metadata-Version: 2.4
Name: kitten-mcp-server
Version: 0.1.0
Summary: MCP Server for Kitten
License: MIT
Classifier: License :: OSI Approved :: MIT License
Classifier: Programming Language :: Python :: 3
Classifier: Operating System :: OS Independent
Requires-Python: >=3.11
License-File: LICENSE
Requires-Dist: fastmcp>=2.0.0
Dynamic: license-file
